strawberryfields/__init__.py
strawberryfields/_version.py
strawberryfields/circuitdrawer.py
strawberryfields/decompositions.py
strawberryfields/device.py
strawberryfields/engine.py
strawberryfields/logger.py
strawberryfields/ops.py
strawberryfields/parameters.py
strawberryfields/plot.py
strawberryfields/program.py
strawberryfields/program_utils.py
strawberryfields/result.py
strawberryfields/apps/__init__.py
strawberryfields/apps/clique.py
strawberryfields/apps/plot.py
strawberryfields/apps/points.py
strawberryfields/apps/sample.py
strawberryfields/apps/similarity.py
strawberryfields/apps/subgraph.py
strawberryfields/apps/data/__init__.py
strawberryfields/apps/data/feature.py
strawberryfields/apps/data/sample.py
strawberryfields/apps/data/feature_data/MUTAG_exact_fv.npy
strawberryfields/apps/data/feature_data/MUTAG_mat.npy
strawberryfields/apps/data/feature_data/QM9_exact_fv.npy
strawberryfields/apps/data/feature_data/QM9_mat.npy
strawberryfields/apps/data/feature_data/QM9_mc_fv.npy
strawberryfields/apps/data/sample_data/MUTAG_0.npz
strawberryfields/apps/data/sample_data/MUTAG_0_A.npz
strawberryfields/apps/data/sample_data/MUTAG_1.npz
strawberryfields/apps/data/sample_data/MUTAG_1_A.npz
strawberryfields/apps/data/sample_data/MUTAG_2.npz
strawberryfields/apps/data/sample_data/MUTAG_2_A.npz
strawberryfields/apps/data/sample_data/MUTAG_3.npz
strawberryfields/apps/data/sample_data/MUTAG_3_A.npz
strawberryfields/apps/data/sample_data/TACE-AS.npz
strawberryfields/apps/data/sample_data/TACE-AS_A.npz
strawberryfields/apps/data/sample_data/formic.npz
strawberryfields/apps/data/sample_data/formic_Ud.npz
strawberryfields/apps/data/sample_data/formic_delta.npz
strawberryfields/apps/data/sample_data/formic_w.npz
strawberryfields/apps/data/sample_data/formic_wp.npz
strawberryfields/apps/data/sample_data/p_hat300-1.npz
strawberryfields/apps/data/sample_data/p_hat300-1_A.npz
strawberryfields/apps/data/sample_data/planted.npz
strawberryfields/apps/data/sample_data/planted_A.npz
StrawberryFields-0.23.0.dist-info/LICENSE
StrawberryFields-0.23.0.dist-info/METADATA
StrawberryFields-0.23.0.dist-info/WHEEL
StrawberryFields-0.23.0.dist-info/top_level.txt
StrawberryFields-0.23.0.dist-info/RECORD
